detroit_live/__init__.py
detroit_live/types.py
detroit_live/dispatch/__init__.py
detroit_live/dispatch/dispatch.py
detroit_live/drag/__init__.py
detroit_live/drag/drag.py
detroit_live/drag/drag_event.py
detroit_live/drag/noevent.py
detroit_live/events/__init__.py
detroit_live/events/base.py
detroit_live/events/context_listener.py
detroit_live/events/event_listeners.py
detroit_live/events/event_producers.py
detroit_live/events/event_source.py
detroit_live/events/headers.py
detroit_live/events/pointer.py
detroit_live/events/tracking_tree.py
detroit_live/events/types.py
detroit_live/events/utils.py
detroit_live/force/__init__.py
detroit_live/force/simulation.py
detroit_live/selection/__init__.py
detroit_live/selection/active.py
detroit_live/selection/app.py
detroit_live/selection/create.py
detroit_live/selection/on.py
detroit_live/selection/select.py
detroit_live/selection/selection.py
detroit_live/selection/shared.py
detroit_live/timer/__init__.py
detroit_live/timer/interval.py
detroit_live/timer/timeout.py
detroit_live/timer/timer.py
detroit_live/zoom/__init__.py
detroit_live/zoom/noevent.py
detroit_live/zoom/transform.py
detroit_live/zoom/zoom.py
detroit_live/zoom/zoom_event.py
detroit_live/zoom/zoom_state.py
detroit_live-0.1.0.dist-info/licenses/LICENSE
detroit_live-0.1.0.dist-info/METADATA
detroit_live-0.1.0.dist-info/WHEEL
detroit_live-0.1.0.dist-info/top_level.txt
detroit_live-0.1.0.dist-info/RECORD
