Metadata-Version: 2.4
Name: detroit-live
Version: 0.1.0
Author-email: Benjamin BOURBON <ben.bourbon06@gmail.com>
Classifier: Programming Language :: Python
Classifier: Programming Language :: Python :: 3.10
Classifier: Programming Language :: Python :: 3.11
Classifier: Programming Language :: Python :: 3.12
Classifier: Topic :: Scientific/Engineering :: Visualization
Requires-Python: >=3.10
License-File: LICENSE
Requires-Dist: lxml
Requires-Dist: detroit==2.6.0
Requires-Dist: quart
Requires-Dist: orjson
Dynamic: license-file
